pyqmri/__init__.py
pyqmri/irgn.py
pyqmri/operator.py
pyqmri/pdsose.py
pyqmri/pyqmri.py
pyqmri/softsense.py
pyqmri/solver.py
pyqmri/streaming.py
pyqmri/transforms.py
pyqmri/_helper_fun/__init__.py
pyqmri/_helper_fun/_calckbkernel.py
pyqmri/_helper_fun/_clprogram.py
pyqmri/_helper_fun/_est_coils.py
pyqmri/_helper_fun/_fftshift2.py
pyqmri/_helper_fun/_fibonacci.py
pyqmri/_helper_fun/_goldcomp.py
pyqmri/_helper_fun/_kb.py
pyqmri/_helper_fun/_nlinvns.py
pyqmri/_helper_fun/_nlinvns_3D.py
pyqmri/_helper_fun/_utils.py
pyqmri/_helper_fun/multislice_viewer.py
pyqmri/kernels/OpenCL_Kernels.c
pyqmri/kernels/OpenCL_Kernels_double.c
pyqmri/kernels/OpenCL_Kernels_double_streamed.c
pyqmri/kernels/OpenCL_Kernels_streamed.c
pyqmri/kernels/OpenCL_gridding_double.c
pyqmri/kernels/OpenCL_gridding_single.c
pyqmri/kernels/OpenCL_gridding_slicefirst_double.c
pyqmri/kernels/OpenCL_gridding_slicefirst_single.c
pyqmri/models/ASL.py
pyqmri/models/B1_comp.py
pyqmri/models/BiExpDecay.py
pyqmri/models/CEST.py
pyqmri/models/DCE_Michal.py
pyqmri/models/Diff.py
pyqmri/models/DiffdirLL.py
pyqmri/models/ExpDecay.py
pyqmri/models/FFC.py
pyqmri/models/FFC_abs.py
pyqmri/models/FFC_phasefit.py
pyqmri/models/FFCsat.py
pyqmri/models/FFCsat_abs.py
pyqmri/models/GeneralModel.py
pyqmri/models/IR.py
pyqmri/models/IRLL.py
pyqmri/models/ImageReco.py
pyqmri/models/Ivim.py
pyqmri/models/IvimDTI.py
pyqmri/models/PASL.py
pyqmri/models/R2Star.py
pyqmri/models/VFA.py
pyqmri/models/__init__.py
pyqmri/models/template.py
pyqmri-1.3.0.dist-info/LICENSE
pyqmri-1.3.0.dist-info/METADATA
pyqmri-1.3.0.dist-info/WHEEL
pyqmri-1.3.0.dist-info/entry_points.txt
pyqmri-1.3.0.dist-info/top_level.txt
pyqmri-1.3.0.dist-info/RECORD
