Metadata-Version: 2.1
Name: pyqmri
Version: 1.3.0
Summary: Model-based parameter quantification using OpenCL and Python
Home-page: https://github.com/IMTtugraz/PyQMRI
Author: Oliver Maier
Author-email: oliver.maier@tugraz.at
License: Apache-2.0
Download-URL: https://github.com/IMTtugraz/PyQMRI/archive/1.2.1.tar.gz
Platform: UNKNOWN
Classifier: Development Status :: 4 - Beta
Classifier: Programming Language :: Python :: 3
Classifier: License :: OSI Approved :: Apache Software License
Classifier: Operating System :: POSIX :: Linux
Requires-Python: >=3.6
Requires-Dist: cython
Requires-Dist: pyopencl
Requires-Dist: numpy
Requires-Dist: h5py
Requires-Dist: mako
Requires-Dist: matplotlib
Requires-Dist: ipyparallel
Requires-Dist: pyfftw
Requires-Dist: pyqt5
Requires-Dist: numexpr
Requires-Dist: sympy (>=1.6.2)
Requires-Dist: inputimeout
Requires-Dist: scipy
